HighLevelBehaviorLanguage/__init__.py
HighLevelBehaviorLanguage/hlb.py
HighLevelBehaviorLanguage/hlb_parser.py
NLP/__init__.py
NLP/nlp.py
NLP/nlplib.py
appJar/__init__.py
appJar/appjar.py
appJar/lib/TkDND_wrapper.py
appJar/lib/__init__.py
appJar/lib/nanojpeg.py
appJar/lib/png.py
appJar/lib/tkinter_png.py
appJar/lib/tooltip.py
dependencyGraph/__init__.py
dependencyGraph/dg.py
deploy/__init__.py
deploy/constraints.py
netxCanvas/__init__.py
netxCanvas/canvas.py
netxCanvas/style.py
output/__init__.py
output/handler.py
topology/__init__.py
topology/topo.py
DEW_ISI-0.0.1.dist-info/LICENSE
DEW_ISI-0.0.1.dist-info/LICENSE~
DEW_ISI-0.0.1.dist-info/METADATA
DEW_ISI-0.0.1.dist-info/WHEEL
DEW_ISI-0.0.1.dist-info/top_level.txt
DEW_ISI-0.0.1.dist-info/RECORD
